odoo/addons/web_sheet_full_width/README.rst
odoo/addons/web_sheet_full_width/__init__.py
odoo/addons/web_sheet_full_width/__manifest__.py
odoo/addons/web_sheet_full_width/i18n/pt_BR.po
odoo/addons/web_sheet_full_width/i18n/web_sheet_full_width.pot
odoo/addons/web_sheet_full_width/readme/CONTRIBUTORS.rst
odoo/addons/web_sheet_full_width/readme/DESCRIPTION.rst
odoo/addons/web_sheet_full_width/static/description/icon.png
odoo/addons/web_sheet_full_width/static/description/index.html
odoo/addons/web_sheet_full_width/static/src/css/web_sheet_full_width.scss
odoo/addons/web_sheet_full_width/templates/assets.xml
odoo12_addon_web_sheet_full_width-12.0.1.0.1.dist-info/METADATA
odoo12_addon_web_sheet_full_width-12.0.1.0.1.dist-info/WHEEL
odoo12_addon_web_sheet_full_width-12.0.1.0.1.dist-info/top_level.txt
odoo12_addon_web_sheet_full_width-12.0.1.0.1.dist-info/RECORD
